.gitignore
.gitlab-ci.yml
LICENSE
README.md
pyproject.toml
setup.cfg
src/plcopen/__init__.py
src/plcopen/access_type.py
src/plcopen/action_qualifier.py
src/plcopen/add_data.py
src/plcopen/add_data_info.py
src/plcopen/body.py
src/plcopen/codesys.py
src/plcopen/connection.py
src/plcopen/connection_point_in.py
src/plcopen/connection_point_out.py
src/plcopen/data_handle_unknown.py
src/plcopen/edge_modifier_type.py
src/plcopen/formatted_text.py
src/plcopen/generate_xsdata_model.ps1
src/plcopen/position.py
src/plcopen/pou_instance.py
src/plcopen/pou_type.py
src/plcopen/project.py
src/plcopen/range_signed.py
src/plcopen/range_unsigned.py
src/plcopen/storage_modifier_type.py
src/plcopen/tc6_xml_v201.xsd
src/plcopen/value.py
src/plcopen/var_list.py
src/plcopen/var_list_access.py
src/plcopen/var_list_config.py
src/plcopen/var_list_plain.py
src/plcopen.egg-info/PKG-INFO
src/plcopen.egg-info/SOURCES.txt
src/plcopen.egg-info/dependency_links.txt
src/plcopen.egg-info/requires.txt
src/plcopen.egg-info/top_level.txt