Metadata-Version: 2.1
Name: plcopen
Version: 1.0.0
Summary: A utility package for PLCopenXML parsing/generation based on xsdata (https://xsdata.readthedocs.io/)
Home-page: 
Author: Matthias Freund
Author-email: matth.freund@gmail.com
Classifier: Programming Language :: Python :: 3
Classifier: License :: OSI Approved :: MIT License
Classifier: Operating System :: OS Independent
Requires-Python: >=3.7
License-File: LICENSE
